swiftex/__init__.py
swiftex/symbols.py
swiftex/abc/__init__.py
swiftex-0.0.4.dist-info/LICENSE
swiftex-0.0.4.dist-info/METADATA
swiftex-0.0.4.dist-info/WHEEL
swiftex-0.0.4.dist-info/top_level.txt
swiftex-0.0.4.dist-info/RECORD
