Metadata-Version: 2.1
Name: swiftex
Version: 0.0.4
Summary: Easy and fast math typesetting with Python
Home-page: https://github.com/mathcube7/swiftex
Author: mathcube
Author-email: mathcube7@gmail.com
License: MIT
Platform: ALL
Classifier: Operating System :: OS Independent
Classifier: Programming Language :: Python :: 3
Requires-Python: >=3.6
License-File: LICENSE
Requires-Dist: sphinx
Requires-Dist: IPython
